stampede/__init__.py
stampede/client.py
stampede/lock.py
stampede/utils.py
stampede/worker.py
stampede-2.0.0.dist-info/AUTHORS.rst
stampede-2.0.0.dist-info/LICENSE
stampede-2.0.0.dist-info/METADATA
stampede-2.0.0.dist-info/WHEEL
stampede-2.0.0.dist-info/top_level.txt
stampede-2.0.0.dist-info/RECORD
