Metadata-Version: 2.1
Name: stampede
Version: 2.0.0
Summary: A really simple job queue. Uses a rudimentary event loop and runs tasks in subprocesses (managed with signalfd). Doesn't support task arguments. Task results are rudimentary (only succcess or failure with exit code). When multiple requests are made for the same task they are collapsed into a single request.
Home-page: https://github.com/ionelmc/python-stampede
Author: Ionel Cristian Mărieș
Author-email: contact@ionelmc.ro
License: BSD 2-Clause License
Platform: UNKNOWN
Classifier: Development Status :: 5 - Production/Stable
Classifier: Intended Audience :: Developers
Classifier: License :: OSI Approved :: BSD License
Classifier: Operating System :: Unix
Classifier: Operating System :: POSIX
Classifier: Operating System :: Microsoft :: Windows
Classifier: Programming Language :: Python
Classifier: Programming Language :: Python :: 2.7
Classifier: Programming Language :: Python :: 3
Classifier: Programming Language :: Python :: 3.5
Classifier: Programming Language :: Python :: 3.6
Classifier: Programming Language :: Python :: 3.7
Classifier: Programming Language :: Python :: Implementation :: CPython
Classifier: Programming Language :: Python :: Implementation :: PyPy
Classifier: Topic :: Utilities
Requires-Dist: signalfd
Requires-Dist: subprocess32
